{
    "status": "OPTIMAL_SOLUTION",
    "solution": {
        "objective": 0.2714508580343221,
        "start_time": [
            [
                161,
                224,
                181,
                371,
                0,
                147,
                25,
                244,
                361,
                218
            ],
            [
                0,
                75,
                1,
                65,
                244,
                180,
                245,
                186,
                55,
                257
            ],
            [
                228,
                180,
                391,
                191,
                108,
                334,
                343,
                357,
                229,
                365
            ],
            [
                402,
                52,
                287,
                286,
                37,
                245,
                130,
                15,
                285,
                0
            ],
            [
                216,
                191,
                361,
                0,
                86,
                189,
                53,
                105,
                287,
                177
            ]
        ],
        "SpeedScaling": [
            [
                1,
                1,
                1,
                1,
                1,
                1,
                1,
                1,
                1,
                1
            ],
            [
                1,
                1,
                1,
                1,
                1,
                1,
                1,
                1,
                1,
                1
            ],
            [
                1,
                1,
                1,
                1,
                1,
                1,
                1,
                1,
                1,
                1
            ],
            [
                1,
                1,
                1,
                1,
                1,
                1,
                1,
                1,
                1,
                1
            ],
            [
                1,
                1,
                1,
                1,
                1,
                1,
                1,
                1,
                1,
                1
            ]
        ],
        "_output_item": "Objective function: 0.2714508580343213 + 8.326672684688674e-16 = 0.2714508580343221 \nObjective function : M-403.0 + E-3953.0 = 0.2714508580343221 \nStart Times: [161, 224, 181, 371, 0, 147, 25, 244, 361, 218, 0, 75, 1, 65, 244, 180, 245, 186, 55, 257, 228, 180, 391, 191, 108, 334, 343, 357, 229, 365, 402, 52, 287, 286, 37, 245, 130, 15, 285, 0, 216, 191, 361, 0, 86, 189, 53, 105, 287, 177]\nSpeed Scaling; [1, 1, 1, 1, 1, 1, 1, 1, 1, 1, 1, 1, 1, 1, 1, 1, 1, 1, 1, 1, 1, 1, 1, 1, 1, 1, 1, 1, 1, 1, 1, 1, 1, 1, 1, 1, 1, 1, 1, 1, 1, 1, 1, 1, 1, 1, 1, 1, 1, 1]\n",
        "_checker": ""
    },
    "statistics": {
        "paths": 0,
        "flatIntVars": 659,
        "flatFloatVars": 48,
        "flatIntConstraints": 802,
        "flatFloatConstraints": 48,
        "evaluatedHalfReifiedConstraints": 200,
        "method": "minimize",
        "flatTime": 113.4,
        "objective": 0.271450858034,
        "objectiveBound": 0.271450858034,
        "nodes": 1168,
        "openNodes": 135,
        "solveTime": 438.0,
        "time": 470.0,
        "nSolutions": 8
    }
}