{
    "status": "SATISFIED",
    "solution": {
        "objective": 0.2523768366464983,
        "start_time": [
            [
                27,
                13,
                244,
                64,
                74
            ],
            [
                21,
                571,
                304,
                179,
                514
            ],
            [
                187,
                504,
                209,
                237,
                43
            ],
            [
                75,
                99,
                382,
                48,
                427
            ],
            [
                33,
                399,
                298,
                5,
                223
            ],
            [
                229,
                153,
                28,
                0,
                146
            ],
            [
                574,
                251,
                168,
                111,
                27
            ],
            [
                267,
                234,
                251,
                24,
                153
            ],
            [
                483,
                329,
                267,
                416,
                618
            ],
            [
                87,
                52,
                507,
                625,
                626
            ],
            [
                0,
                359,
                205,
                257,
                209
            ],
            [
                4,
                204,
                127,
                171,
                365
            ],
            [
                564,
                40,
                523,
                500,
                545
            ],
            [
                547,
                0,
                119,
                619,
                612
            ],
            [
                514,
                27,
                547,
                180,
                500
            ],
            [
                338,
                78,
                19,
                510,
                298
            ],
            [
                113,
                129,
                2,
                106,
                0
            ],
            [
                209,
                563,
                441,
                483,
                2
            ],
            [
                127,
                312,
                125,
                66,
                329
            ],
            [
                507,
                625,
                443,
                601,
                619
            ]
        ],
        "SpeedScaling": [
            [
                1,
                1,
                1,
                1,
                1
            ],
            [
                1,
                1,
                1,
                1,
                1
            ],
            [
                1,
                1,
                1,
                1,
                1
            ],
            [
                1,
                1,
                1,
                1,
                1
            ],
            [
                1,
                1,
                1,
                1,
                1
            ],
            [
                1,
                1,
                1,
                1,
                1
            ],
            [
                1,
                1,
                1,
                1,
                1
            ],
            [
                1,
                1,
                1,
                1,
                1
            ],
            [
                1,
                1,
                1,
                1,
                1
            ],
            [
                1,
                1,
                1,
                1,
                1
            ],
            [
                1,
                1,
                1,
                1,
                1
            ],
            [
                1,
                1,
                1,
                1,
                1
            ],
            [
                1,
                1,
                1,
                1,
                1
            ],
            [
                1,
                1,
                1,
                1,
                1
            ],
            [
                1,
                1,
                1,
                1,
                1
            ],
            [
                1,
                1,
                1,
                1,
                1
            ],
            [
                1,
                1,
                1,
                1,
                1
            ],
            [
                1,
                1,
                1,
                1,
                1
            ],
            [
                1,
                1,
                1,
                1,
                1
            ],
            [
                1,
                1,
                1,
                1,
                1
            ]
        ],
        "_output_item": "Objective function: 0.2523768366464996 + -1.221245327087672e-15 = 0.2523768366464983 \nObjective function : M-627.0 + E-8052.0 = 0.2523768366464983 \nStart Times: [27, 13, 244, 64, 74, 21, 571, 304, 179, 514, 187, 504, 209, 237, 43, 75, 99, 382, 48, 427, 33, 399, 298, 5, 223, 229, 153, 28, 0, 146, 574, 251, 168, 111, 27, 267, 234, 251, 24, 153, 483, 329, 267, 416, 618, 87, 52, 507, 625, 626, 0, 359, 205, 257, 209, 4, 204, 127, 171, 365, 564, 40, 523, 500, 545, 547, 0, 119, 619, 612, 514, 27, 547, 180, 500, 338, 78, 19, 510, 298, 113, 129, 2, 106, 0, 209, 563, 441, 483, 2, 127, 312, 125, 66, 329, 507, 625, 443, 601, 619]\nSpeed Scaling; [1, 1, 1, 1, 1, 1, 1, 1, 1, 1, 1, 1, 1, 1, 1, 1, 1, 1, 1, 1, 1, 1, 1, 1, 1, 1, 1, 1, 1, 1, 1, 1, 1, 1, 1, 1, 1, 1, 1, 1, 1, 1, 1, 1, 1, 1, 1, 1, 1, 1, 1, 1, 1, 1, 1, 1, 1, 1, 1, 1, 1, 1, 1, 1, 1, 1, 1, 1, 1, 1, 1, 1, 1, 1, 1, 1, 1, 1, 1, 1, 1, 1, 1, 1, 1, 1, 1, 1, 1, 1, 1, 1, 1, 1, 1, 1, 1, 1, 1, 1]\n",
        "_checker": ""
    },
    "statistics": {
        "paths": 0,
        "flatIntVars": 2671,
        "flatFloatVars": 98,
        "flatIntConstraints": 3627,
        "flatFloatConstraints": 98,
        "evaluatedHalfReifiedConstraints": 1900,
        "method": "minimize",
        "flatTime": 375.05699999999996,
        "objective": 0.252376836646,
        "objectiveBound": 0.117979028486,
        "nodes": 19512,
        "openNodes": 12921,
        "solveTime": 30923.0,
        "time": 22138.0,
        "nSolutions": 11
    }
}