{
    "status": "SATISFIED",
    "solution": {
        "objective": 0.1132020845396644,
        "start_time": [
            [
                1813,
                1008,
                3176,
                800,
                0,
                1257,
                3028,
                1624,
                1867,
                3819,
                2550,
                246,
                3370,
                2751,
                2915,
                3295,
                2860,
                205,
                1394,
                439,
                1707,
                2687,
                3561,
                3774,
                1139
            ],
            [
                2366,
                1790,
                1343,
                3181,
                1445,
                2581,
                2449,
                1984,
                2984,
                2129,
                0,
                1680,
                232,
                3758,
                94,
                1572,
                1939,
                3249,
                1261,
                2852,
                1006,
                3622,
                3798,
                3080,
                319
            ],
            [
                1094,
                2239,
                995,
                1947,
                1707,
                3360,
                598,
                2550,
                549,
                135,
                2323,
                1187,
                3586,
                3122,
                1524,
                1839,
                3767,
                2703,
                2060,
                1377,
                3195,
                2843,
                774,
                0,
                2972
            ],
            [
                3188,
                2522,
                2581,
                621,
                3088,
                1533,
                3738,
                1762,
                321,
                2644,
                800,
                3414,
                2438,
                2860,
                1325,
                1947,
                1147,
                1026,
                3845,
                0,
                3590,
                549,
                177,
                2117,
                1440
            ],
            [
                2245,
                315,
                90,
                1783,
                1168,
                948,
                2797,
                2703,
                1037,
                1318,
                2029,
                1414,
                3749,
                1634,
                0,
                2193,
                2366,
                3611,
                786,
                3227,
                608,
                1947,
                421,
                1573,
                3122
            ],
            [
                613,
                2581,
                0,
                3391,
                3915,
                3256,
                774,
                540,
                3080,
                3150,
                3622,
                1996,
                2799,
                407,
                1151,
                90,
                2225,
                263,
                961,
                4039,
                3738,
                3477,
                1216,
                312,
                2302
            ],
            [
                738,
                1261,
                3635,
                3286,
                2676,
                1920,
                2618,
                902,
                1168,
                1414,
                1747,
                2926,
                998,
                3195,
                312,
                2556,
                169,
                1793,
                1193,
                3479,
                2806,
                0,
                1575,
                2315,
                3728
            ],
            [
                3078,
                3188,
                2644,
                2060,
                233,
                2223,
                0,
                3305,
                2830,
                3678,
                1026,
                3802,
                2268,
                128,
                3947,
                1202,
                3396,
                474,
                1651,
                1524,
                395,
                2438,
                2973,
                3524,
                623
            ],
            [
                197,
                699,
                1094,
                329,
                2335,
                1394,
                427,
                3586,
                47,
                836,
                530,
                1790,
                3561,
                3286,
                2574,
                3774,
                2038,
                2452,
                2738,
                1235,
                1996,
                2146,
                3986,
                3687,
                905
            ],
            [
                2449,
                1139,
                2004,
                3069,
                1839,
                691,
                1267,
                3012,
                0,
                2852,
                3411,
                439,
                1358,
                233,
                1238,
                3870,
                3611,
                3478,
                2605,
                2718,
                856,
                1456,
                3181,
                542,
                47
            ]
        ],
        "SpeedScaling": [
            [
                1,
                1,
                1,
                1,
                1,
                1,
                1,
                1,
                1,
                1,
                1,
                1,
                1,
                1,
                1,
                1,
                1,
                1,
                1,
                1,
                1,
                1,
                1,
                1,
                1
            ],
            [
                1,
                1,
                1,
                1,
                1,
                1,
                1,
                1,
                1,
                1,
                1,
                1,
                1,
                1,
                1,
                1,
                1,
                1,
                1,
                1,
                1,
                1,
                1,
                1,
                1
            ],
            [
                1,
                1,
                1,
                1,
                1,
                1,
                1,
                1,
                1,
                1,
                1,
                1,
                1,
                1,
                1,
                1,
                1,
                1,
                1,
                1,
                1,
                1,
                1,
                1,
                1
            ],
            [
                1,
                1,
                1,
                1,
                1,
                1,
                1,
                1,
                1,
                1,
                1,
                1,
                1,
                1,
                1,
                1,
                1,
                1,
                1,
                1,
                1,
                1,
                1,
                1,
                1
            ],
            [
                1,
                1,
                1,
                1,
                1,
                1,
                1,
                1,
                1,
                1,
                1,
                1,
                1,
                1,
                1,
                1,
                1,
                1,
                1,
                1,
                1,
                1,
                1,
                1,
                1
            ],
            [
                1,
                1,
                1,
                1,
                1,
                1,
                1,
                1,
                1,
                1,
                1,
                1,
                1,
                1,
                1,
                1,
                1,
                1,
                1,
                1,
                1,
                1,
                1,
                1,
                1
            ],
            [
                1,
                1,
                1,
                1,
                1,
                1,
                1,
                1,
                1,
                1,
                1,
                1,
                1,
                1,
                1,
                1,
                1,
                1,
                1,
                1,
                1,
                1,
                1,
                1,
                1
            ],
            [
                1,
                1,
                1,
                1,
                1,
                1,
                1,
                1,
                1,
                1,
                1,
                1,
                1,
                1,
                1,
                1,
                1,
                1,
                1,
                1,
                1,
                1,
                1,
                1,
                1
            ],
            [
                1,
                1,
                1,
                1,
                1,
                1,
                1,
                1,
                1,
                1,
                1,
                1,
                1,
                1,
                1,
                1,
                1,
                1,
                1,
                1,
                1,
                1,
                1,
                1,
                1
            ],
            [
                1,
                1,
                1,
                1,
                1,
                1,
                1,
                1,
                1,
                1,
                1,
                1,
                1,
                1,
                1,
                1,
                1,
                1,
                1,
                1,
                1,
                1,
                1,
                1,
                1
            ]
        ],
        "_output_item": "Objective function: 0.113202084539664 + 3.83373888190874e-16 = 0.1132020845396644 \nObjective function : M-4184.0 + E-7791.0 = 0.1132020845396644 \nStart Times: [1813, 1008, 3176, 800, 0, 1257, 3028, 1624, 1867, 3819, 2550, 246, 3370, 2751, 2915, 3295, 2860, 205, 1394, 439, 1707, 2687, 3561, 3774, 1139, 2366, 1790, 1343, 3181, 1445, 2581, 2449, 1984, 2984, 2129, 0, 1680, 232, 3758, 94, 1572, 1939, 3249, 1261, 2852, 1006, 3622, 3798, 3080, 319, 1094, 2239, 995, 1947, 1707, 3360, 598, 2550, 549, 135, 2323, 1187, 3586, 3122, 1524, 1839, 3767, 2703, 2060, 1377, 3195, 2843, 774, 0, 2972, 3188, 2522, 2581, 621, 3088, 1533, 3738, 1762, 321, 2644, 800, 3414, 2438, 2860, 1325, 1947, 1147, 1026, 3845, 0, 3590, 549, 177, 2117, 1440, 2245, 315, 90, 1783, 1168, 948, 2797, 2703, 1037, 1318, 2029, 1414, 3749, 1634, 0, 2193, 2366, 3611, 786, 3227, 608, 1947, 421, 1573, 3122, 613, 2581, 0, 3391, 3915, 3256, 774, 540, 3080, 3150, 3622, 1996, 2799, 407, 1151, 90, 2225, 263, 961, 4039, 3738, 3477, 1216, 312, 2302, 738, 1261, 3635, 3286, 2676, 1920, 2618, 902, 1168, 1414, 1747, 2926, 998, 3195, 312, 2556, 169, 1793, 1193, 3479, 2806, 0, 1575, 2315, 3728, 3078, 3188, 2644, 2060, 233, 2223, 0, 3305, 2830, 3678, 1026, 3802, 2268, 128, 3947, 1202, 3396, 474, 1651, 1524, 395, 2438, 2973, 3524, 623, 197, 699, 1094, 329, 2335, 1394, 427, 3586, 47, 836, 530, 1790, 3561, 3286, 2574, 3774, 2038, 2452, 2738, 1235, 1996, 2146, 3986, 3687, 905, 2449, 1139, 2004, 3069, 1839, 691, 1267, 3012, 0, 2852, 3411, 439, 1358, 233, 1238, 3870, 3611, 3478, 2605, 2718, 856, 1456, 3181, 542, 47]\nSpeed Scaling; [1, 1, 1, 1, 1, 1, 1, 1, 1, 1, 1, 1, 1, 1, 1, 1, 1, 1, 1, 1, 1, 1, 1, 1, 1, 1, 1, 1, 1, 1, 1, 1, 1, 1, 1, 1, 1, 1, 1, 1, 1, 1, 1, 1, 1, 1, 1, 1, 1, 1, 1, 1, 1, 1, 1, 1, 1, 1, 1, 1, 1, 1, 1, 1, 1, 1, 1, 1, 1, 1, 1, 1, 1, 1, 1, 1, 1, 1, 1, 1, 1, 1, 1, 1, 1, 1, 1, 1, 1, 1, 1, 1, 1, 1, 1, 1, 1, 1, 1, 1, 1, 1, 1, 1, 1, 1, 1, 1, 1, 1, 1, 1, 1, 1, 1, 1, 1, 1, 1, 1, 1, 1, 1, 1, 1, 1, 1, 1, 1, 1, 1, 1, 1, 1, 1, 1, 1, 1, 1, 1, 1, 1, 1, 1, 1, 1, 1, 1, 1, 1, 1, 1, 1, 1, 1, 1, 1, 1, 1, 1, 1, 1, 1, 1, 1, 1, 1, 1, 1, 1, 1, 1, 1, 1, 1, 1, 1, 1, 1, 1, 1, 1, 1, 1, 1, 1, 1, 1, 1, 1, 1, 1, 1, 1, 1, 1, 1, 1, 1, 1, 1, 1, 1, 1, 1, 1, 1, 1, 1, 1, 1, 1, 1, 1, 1, 1, 1, 1, 1, 1, 1, 1, 1, 1, 1, 1, 1, 1, 1, 1, 1, 1, 1, 1, 1, 1, 1, 1, 1, 1, 1, 1, 1, 1, 1, 1, 1, 1, 1, 1]\n",
        "_checker": ""
    },
    "statistics": {
        "paths": 0,
        "flatBoolVars": 2250,
        "flatIntVars": 1501,
        "flatFloatVars": 254,
        "flatBoolConstraints": 1125,
        "flatIntConstraints": 6251,
        "flatFloatConstraints": 254,
        "evaluatedHalfReifiedConstraints": 2250,
        "method": "minimize",
        "flatTime": 190.525,
        "time": 3064.0,
        "initTime": 37.682,
        "solveTime": 108052.0,
        "solutions": 5,
        "variables": 3751,
        "propagators": 7630,
        "propagations": 2659458513,
        "nodes": 10269767,
        "failures": 5134481,
        "restarts": 0,
        "peakDepth": 440,
        "nSolutions": 5
    }
}