{
    "status": "SATISFIED",
    "solution": {
        "objective": 0.5960807299298151,
        "start_time": [
            [
                770,
                810,
                1459,
                360,
                302,
                994,
                1259,
                80,
                442,
                1226,
                697,
                854,
                585,
                1050,
                397,
                129,
                1406,
                486,
                1187,
                212
            ],
            [
                1404,
                962,
                593,
                40,
                1205,
                1158,
                299,
                684,
                1337,
                636,
                1535,
                1565,
                1116,
                152,
                471,
                788,
                421,
                742,
                814,
                1070
            ],
            [
                302,
                764,
                1256,
                172,
                1119,
                549,
                423,
                958,
                629,
                269,
                362,
                797,
                1159,
                525,
                124,
                90,
                468,
                853,
                1018,
                669
            ],
            [
                100,
                1459,
                1329,
                462,
                1036,
                732,
                512,
                879,
                980,
                302,
                645,
                1270,
                697,
                406,
                212,
                1134,
                929,
                1087,
                346,
                169
            ],
            [
                1355,
                323,
                1136,
                807,
                472,
                637,
                1083,
                287,
                260,
                684,
                1397,
                222,
                932,
                1188,
                432,
                43,
                1530,
                143,
                0,
                87
            ]
        ],
        "SpeedScaling": [
            [
                2,
                3,
                1,
                2,
                2,
                1,
                1,
                2,
                2,
                2,
                1,
                1,
                1,
                1,
                2,
                2,
                2,
                1,
                2,
                1
            ],
            [
                1,
                1,
                2,
                1,
                1,
                2,
                1,
                2,
                1,
                2,
                2,
                2,
                2,
                1,
                1,
                1,
                1,
                2,
                1,
                2
            ],
            [
                2,
                3,
                1,
                1,
                2,
                1,
                3,
                2,
                3,
                2,
                2,
                1,
                1,
                3,
                2,
                2,
                1,
                1,
                1,
                1
            ],
            [
                1,
                1,
                1,
                2,
                2,
                1,
                1,
                2,
                2,
                2,
                2,
                2,
                1,
                2,
                1,
                1,
                2,
                2,
                1,
                2
            ],
            [
                1,
                1,
                2,
                1,
                1,
                2,
                2,
                3,
                1,
                1,
                1,
                1,
                1,
                1,
                3,
                3,
                1,
                1,
                2,
                1
            ]
        ],
        "_output_item": "Objective function normalized: M-0.07315676449534717 + E-0.4807731024763437 + T-0.04215086295812417 = 0.5960807299298151 \nObjective function : M-1595.0 + E-5146.0 + T-612.9999999999999 = 0.5960807299298151 \nStart Times: [770, 810, 1459, 360, 302, 994, 1259, 80, 442, 1226, 697, 854, 585, 1050, 397, 129, 1406, 486, 1187, 212, 1404, 962, 593, 40, 1205, 1158, 299, 684, 1337, 636, 1535, 1565, 1116, 152, 471, 788, 421, 742, 814, 1070, 302, 764, 1256, 172, 1119, 549, 423, 958, 629, 269, 362, 797, 1159, 525, 124, 90, 468, 853, 1018, 669, 100, 1459, 1329, 462, 1036, 732, 512, 879, 980, 302, 645, 1270, 697, 406, 212, 1134, 929, 1087, 346, 169, 1355, 323, 1136, 807, 472, 637, 1083, 287, 260, 684, 1397, 222, 932, 1188, 432, 43, 1530, 143, 0, 87]\nSpeed Scaling; [2, 3, 1, 2, 2, 1, 1, 2, 2, 2, 1, 1, 1, 1, 2, 2, 2, 1, 2, 1, 1, 1, 2, 1, 1, 2, 1, 2, 1, 2, 2, 2, 2, 1, 1, 1, 1, 2, 1, 2, 2, 3, 1, 1, 2, 1, 3, 2, 3, 2, 2, 1, 1, 3, 2, 2, 1, 1, 1, 1, 1, 1, 1, 2, 2, 1, 1, 2, 2, 2, 2, 2, 1, 2, 1, 1, 2, 2, 1, 2, 1, 1, 2, 1, 1, 2, 2, 3, 1, 1, 1, 1, 1, 1, 3, 3, 1, 1, 2, 1]\n",
        "_checker": ""
    },
    "statistics": {
        "paths": 0,
        "flatIntVars": 1337,
        "flatFloatVars": 110,
        "flatIntConstraints": 2402,
        "flatFloatConstraints": 110,
        "evaluatedHalfReifiedConstraints": 400,
        "method": "minimize",
        "flatTime": 206.369,
        "objective": 0.59608072993,
        "objectiveBound": 0.585341527375,
        "nodes": 59496,
        "solveTime": 57507.8,
        "time": 57464.0,
        "openNodes": 29826,
        "nSolutions": 24
    }
}